perculus_sdk/__init__.py
perculus_sdk/auth.py
perculus_sdk/client.py
perculus_sdk/attendee/__init__.py
perculus_sdk/attendee/client.py
perculus_sdk/session/__init__.py
perculus_sdk/session/client.py
perculus_sdk/user/__init__.py
perculus_sdk/user/client.py
perculus_sdk-0.2.5.dist-info/METADATA
perculus_sdk-0.2.5.dist-info/WHEEL
perculus_sdk-0.2.5.dist-info/top_level.txt
perculus_sdk-0.2.5.dist-info/RECORD
